{
  "video_id": "ewq7ALt4uD0",
  "duration_seconds": 41,
  "wps": 3.54,
  "total_words": 145,
  "language_mix": {
    "hindi": 0.0,
    "english": 100.0,
    "total_chars": 609
  },
  "hook": {
    "type": "question",
    "text": "Only ancient India could design this. It looks like a simple pot, but the design is really clever. Sometimes washing hands is terrifying. If your hands are"
  },
  "closing": {
    "type": "direct_cta",
    "text": "It's a perfectly shaped drinking glass [music] hidden in plain sight. One pot, three solutions. For more design wisdom, subscribe."
  },
  "audience_addressing": [
    "you (English)",
    "conditional address (if you...)"
  ],
  "structure": "standard_short",
  "top_words": [
    {
      "word": "it",
      "count": 6
    },
    {
      "word": "the",
      "count": 5
    },
    {
      "word": "is",
      "count": 5
    },
    {
      "word": "and",
      "count": 4
    },
    {
      "word": "design",
      "count": 3
    },
    {
      "word": "this",
      "count": 3
    },
    {
      "word": "pot",
      "count": 3
    },
    {
      "word": "but",
      "count": 3
    },
    {
      "word": "your",
      "count": 3
    },
    {
      "word": "you",
      "count": 3
    },
    {
      "word": "it's",
      "count": 3
    },
    {
      "word": "hands",
      "count": 2
    },
    {
      "word": "dirty",
      "count": 2
    },
    {
      "word": "shaped",
      "count": 2
    },
    {
      "word": "to",
      "count": 2
    },
    {
      "word": "put",
      "count": 2
    },
    {
      "word": "on",
      "count": 2
    },
    {
      "word": "of",
      "count": 2
    },
    {
      "word": "one",
      "count": 2
    },
    {
      "word": "not",
      "count": 2
    }
  ],
  "top_bigrams": [
    {
      "phrase": "it's a",
      "count": 2
    },
    {
      "phrase": "but this",
      "count": 2
    },
    {
      "phrase": "on a",
      "count": 2
    },
    {
      "phrase": "only ancient",
      "count": 1
    },
    {
      "phrase": "ancient india",
      "count": 1
    },
    {
      "phrase": "india could",
      "count": 1
    },
    {
      "phrase": "could design",
      "count": 1
    },
    {
      "phrase": "design this",
      "count": 1
    },
    {
      "phrase": "this it",
      "count": 1
    },
    {
      "phrase": "it looks",
      "count": 1
    }
  ],
  "segment_count": 5
}