{
  "video_id": "iQ4HGIGIY00",
  "duration_seconds": 60,
  "wps": 2.95,
  "total_words": 177,
  "language_mix": {
    "hindi": 0.0,
    "english": 100.0,
    "total_chars": 852
  },
  "hook": {
    "type": "general_statement",
    "text": "Luxury leather means chemicals, waste,"
  },
  "closing": {
    "type": "punchline_or_open",
    "text": "leather?"
  },
  "audience_addressing": [
    "you (English)"
  ],
  "structure": "long_form_story",
  "top_words": [
    {
      "word": "leather",
      "count": 8
    },
    {
      "word": "waste",
      "count": 6
    },
    {
      "word": "and",
      "count": 5
    },
    {
      "word": "the",
      "count": 5
    },
    {
      "word": "are",
      "count": 5
    },
    {
      "word": "into",
      "count": 4
    },
    {
      "word": "from",
      "count": 4
    },
    {
      "word": "which",
      "count": 4
    },
    {
      "word": "is",
      "count": 4
    },
    {
      "word": "what",
      "count": 3
    },
    {
      "word": "brands",
      "count": 3
    },
    {
      "word": "it",
      "count": 3
    },
    {
      "word": "animal",
      "count": 2
    },
    {
      "word": "but",
      "count": 2
    },
    {
      "word": "not",
      "count": 2
    },
    {
      "word": "you",
      "count": 2
    },
    {
      "word": "we",
      "count": 2
    },
    {
      "word": "apple",
      "count": 2
    },
    {
      "word": "made",
      "count": 2
    },
    {
      "word": "turn",
      "count": 2
    }
  ],
  "top_bigrams": [
    {
      "phrase": "waste into",
      "count": 3
    },
    {
      "phrase": "made from",
      "count": 2
    },
    {
      "phrase": "it is",
      "count": 2
    },
    {
      "phrase": "which are",
      "count": 2
    },
    {
      "phrase": "luxury leather",
      "count": 1
    },
    {
      "phrase": "leather means",
      "count": 1
    },
    {
      "phrase": "means chemicals",
      "count": 1
    },
    {
      "phrase": "chemicals waste",
      "count": 1
    },
    {
      "phrase": "waste and",
      "count": 1
    },
    {
      "phrase": "and animal",
      "count": 1
    }
  ],
  "segment_count": 29
}