{
  "video_id": "y79ENCwO3xY",
  "duration_seconds": 72,
  "wps": 2.78,
  "total_words": 200,
  "language_mix": {
    "hindi": 0.0,
    "english": 100.0,
    "total_chars": 893
  },
  "hook": {
    "type": "statement",
    "text": "This drone is smaller than a bird, but it is the Indian army's deadliest secret weapon. It was designed to solve a massive problem that normal military"
  },
  "closing": {
    "type": "direct_cta",
    "text": "Subscribe for more."
  },
  "audience_addressing": [
    "neutral/third_person"
  ],
  "structure": "detailed_explainer",
  "top_words": [
    {
      "word": "it",
      "count": 11
    },
    {
      "word": "the",
      "count": 10
    },
    {
      "word": "and",
      "count": 6
    },
    {
      "word": "in",
      "count": 5
    },
    {
      "word": "is",
      "count": 4
    },
    {
      "word": "but",
      "count": 4
    },
    {
      "word": "they",
      "count": 4
    },
    {
      "word": "to",
      "count": 3
    },
    {
      "word": "even",
      "count": 3
    },
    {
      "word": "no",
      "count": 3
    },
    {
      "word": "enemy",
      "count": 3
    },
    {
      "word": "if",
      "count": 3
    },
    {
      "word": "this",
      "count": 2
    },
    {
      "word": "drone",
      "count": 2
    },
    {
      "word": "army's",
      "count": 2
    },
    {
      "word": "that",
      "count": 2
    },
    {
      "word": "drones",
      "count": 2
    },
    {
      "word": "see",
      "count": 2
    },
    {
      "word": "are",
      "count": 2
    },
    {
      "word": "enemies",
      "count": 2
    }
  ],
  "top_bigrams": [
    {
      "phrase": "it is",
      "count": 2
    },
    {
      "phrase": "in the",
      "count": 2
    },
    {
      "phrase": "and its",
      "count": 2
    },
    {
      "phrase": "absolutely no",
      "count": 2
    },
    {
      "phrase": "the enemy",
      "count": 2
    },
    {
      "phrase": "this drone",
      "count": 1
    },
    {
      "phrase": "drone is",
      "count": 1
    },
    {
      "phrase": "is smaller",
      "count": 1
    },
    {
      "phrase": "smaller than",
      "count": 1
    },
    {
      "phrase": "than a",
      "count": 1
    }
  ],
  "segment_count": 10
}