{
  "video_id": "KNs2b7_Rowo",
  "title": "Biggest Copy-Cat Brands - Part 2",
  "channel": "designbyarpit",
  "description": "#Shorts #YouTubeShorts #Viral #Trending #Copycat #Knockoff #Dupes #BrandCopy #Packaging #RealVsFake #BrandWars #DeceptivePackaging #Marketing #Funny #Consumer #SpotTheDifference #ProductReview",
  "duration_seconds": 51,
  "publish_date": "20251005",
  "transcript_status": "OK",
  "transcript_language": "unknown",
  "transcript_source": "chrome-headless",
  "segment_count": 7,
  "ingested_at": "2026-03-20T18:59:26.070695+00:00"
}