{
  "video_id": "ixg4-FjkO-I",
  "title": "Shark tank Reality?",
  "channel": "ThinkSchool_Hindi",
  "description": "👉India’s first ‘learn by doing’ experience for growing your wealth. Imagine being able to build your own personal finance plan while attending a class, live. Apply to this upcoming FREE class this week here on Zerodha Varsity: https://openinapp.link/tsje3\n\n👉By Think School: https://thethinkschool.com/\n\n👉VIDEO INTRODUCTION:\n\n\n\n►►Check out Think School: https://thethinkschool.com/sp/communication-masterclass/\n►►ThinkSchool English \nhttps://www.youtube.com/@ThinkSchool\n\n\n►►Check out Zerodha - https://www.youtube.com/@UC59YUBhNLMkS2Q8NBWBGHAA \n\nCredits: CNN-News 18, WION, NBC News, Money control pro, Business standard, TV18,Business Today, ABC news, CNBC, ET now ,Bloomberg originals, Financial Times, DW documentary, AL Jazeera English, BBC news, Firstpost. \n\nFair use - This video is for educational purposes only. All materials used in this video, including images, audio, and video clips, are the property of their respective owners and are used here under the doctrine of fair use. This video is intended to provide commentary, criticism, research, and education on the subject matter. We believe this constitutes a fair use of any such copyrighted material as provided for in Section 107 of the US Copyright Law.\n\n#business #thinkschoolhindi #indianbusinessclass",
  "duration_seconds": 77,
  "publish_date": "20250326",
  "transcript_status": "NO_TRANSCRIPT",
  "transcript_language": null,
  "transcript_source": null,
  "segment_count": 0,
  "ingested_at": "2026-05-14T00:07:16.319620+00:00",
  "error": "All extraction methods failed"
}