{
  "video_id": "iUB6_pwtzEc",
  "duration_seconds": 35,
  "wps": 4.8,
  "total_words": 168,
  "language_mix": {
    "hindi": 99.5,
    "english": 0.5,
    "total_chars": 565
  },
  "hook": {
    "type": "statement",
    "text": "ये जोमato ब्लिंकिट वालों को लोग जहां पे देख रहे हैं वहीं पे लूट ले रहे हैं। तुम इनकी सबसे बड़ी प्रॉब्लम समझो। जब ये लोग शुरू-शुर में मार्केट के अंदर आए थे तो"
  },
  "closing": {
    "type": "punchline_or_open",
    "text": "रिफंड नहीं मिला तो वो कंज्यूमर को उठा सकते हैं और उसके बाद 10-15000 देने पड़ेंगे।"
  },
  "audience_addressing": [
    "भाई/भैया (bro-style)",
    "आप (formal)"
  ],
  "structure": "standard_short",
  "top_words": [
    {
      "word": "हैं",
      "count": 10
    },
    {
      "word": "रहे",
      "count": 8
    },
    {
      "word": "तो",
      "count": 6
    },
    {
      "word": "लोग",
      "count": 5
    },
    {
      "word": "और",
      "count": 5
    },
    {
      "word": "में",
      "count": 4
    },
    {
      "word": "रिफंड",
      "count": 4
    },
    {
      "word": "कर",
      "count": 4
    },
    {
      "word": "उसको",
      "count": 4
    },
    {
      "word": "को",
      "count": 3
    },
    {
      "word": "पे",
      "count": 3
    },
    {
      "word": "के",
      "count": 3
    },
    {
      "word": "थे",
      "count": 3
    },
    {
      "word": "अंडे",
      "count": 3
    },
    {
      "word": "ये",
      "count": 2
    },
    {
      "word": "आए",
      "count": 2
    },
    {
      "word": "कि",
      "count": 2
    },
    {
      "word": "भैया",
      "count": 2
    },
    {
      "word": "भी",
      "count": 2
    },
    {
      "word": "है",
      "count": 2
    }
  ],
  "top_bigrams": [
    {
      "phrase": "रहे हैं",
      "count": 8
    },
    {
      "phrase": "हैं और",
      "count": 4
    },
    {
      "phrase": "कि भैया",
      "count": 2
    },
    {
      "phrase": "तो पैसे",
      "count": 2
    },
    {
      "phrase": "पैसे रिफंड",
      "count": 2
    },
    {
      "phrase": "कर रहे",
      "count": 2
    },
    {
      "phrase": "और उसको",
      "count": 2
    },
    {
      "phrase": "बोल रहे",
      "count": 2
    },
    {
      "phrase": "अंडे टूटे",
      "count": 2
    },
    {
      "phrase": "टूटे हुए",
      "count": 2
    }
  ],
  "segment_count": 5
}