{
  "creator": "ThinkSchool_Hindi",
  "transcript_hashes": {
    "-u_oecqIQyo": "254cc4e1ab074122",
    "2QFAaiBrCkg": "d87f5890413d85bb",
    "2rTZI1j6YkY": "9e3e4ab36c33e497",
    "4HLsppEwOQU": "a609c56656b287a0",
    "6v9V_HR3l1M": "1d002a9069cf8de1",
    "75wmrQQwRaI": "5e9f6d5fcdb751b8",
    "85Wjf3lXpZw": "5c5c17f7edd1d27a",
    "8vju_r7aRlM": "3eea3e2f859c7657",
    "99PlwlvthQk": "e850cc759617d6b0",
    "Afub1qCCEyY": "ee292bad1abb96bf",
    "AnY8Ozmvbwg": "2583f10848d823eb",
    "DfalmzBOoUg": "2cd002966de1263f",
    "Fjb2_nmckTc": "5500db2e219fa9f8",
    "GBtQnM9Wzvg": "c59db613c0dffd22",
    "HizrianHUbk": "28c435cc946846a5",
    "HyedRhCk0Os": "3b0acef1a14a5e3b",
    "JwdYM_9z0fo": "39130d6aacac7e47",
    "K3X2EEi5ozM": "461a640a51ab4719",
    "KiwZepUoiA0": "645956db17701d78",
    "L23VXdu9VjU": "ac712c08294baac7",
    "NGk85Xwh88k": "24cd42b49bdc528c",
    "Q3A_Spj1Wvg": "e6e693ede317e528",
    "S5A93X6GrQ4": "aecbcfe9aead4739",
    "Y357sI8I4mo": "d2d8e62ce0574e86",
    "YzzTSk5hurY": "cf85075ee66ab65b",
    "ZMmfkpfUFW4": "43fbcf4ea991a8f8",
    "bj-eOWsjMe0": "fb0c3e4ad1993cd3",
    "cIM5ZTAUH40": "084c64972cee7872",
    "duRjwK6rIG4": "efef8cb7b9ed011a",
    "gIajzDJY72I": "06c46a4d74817626",
    "ip6XMkqLNhI": "a609869ded6aef14",
    "jfaQ3TwGldA": "81b9ecd0bb25e2cd",
    "kKOgxrsShIE": "cf8cd9b313e20d0e",
    "knLbBIdJr3A": "901ea54ac205cde0",
    "knViZGB9w64": "746acd31bdec8f1a",
    "kpaHJUAbbQE": "b61b1580761bc958",
    "lLbkBKRTXH4": "aa26eb432d85ee7e",
    "nXHX3NpkAnk": "2a5e65d10cb6fb38",
    "oCp0fJ624so": "da50879726af29c9",
    "opgxyrwlF1Q": "5d53eda8abb541e9",
    "tFQ1LaILLgg": "51c3cf04273c6752",
    "wFETePdu-l4": "c807ce5e042e38f6",
    "wMJze_OLPJs": "726a79b5d9eddd4c",
    "xpC8Vlezyf8": "6b50585f9ad4c46f"
  },
  "videos_analyzed": 44,
  "videos_available": 44,
  "last_updated": "2026-03-29T12:33:50.466745"
}