{
  "video_id": "eZJ-m3qWlHI",
  "title": "Apki Worth Kya Hai? #apratihast #rich",
  "channel": "AshutoshPratihastAP",
  "description": "Know Your Worth🔥\n\nWhere You Stand..\nWhat You Are Meant For..\nWhat You Can Do..\nFor Yourself & Others✨\n\nPinning the Best Comment📌\n\n#apratihast #worth #inspirational #igdaily #idigitalpreneur",
  "duration_seconds": 53,
  "publish_date": "20240106",
  "transcript_status": "OK",
  "transcript_language": "Hindi (auto-generated)",
  "transcript_source": "youtube-transcript-api",
  "segment_count": 18,
  "ingested_at": "2026-03-17T00:55:16.456557+00:00"
}